Metadata-Version: 1.0
Name: timyang-distributions
Version: 0.1
Summary: Gaussian and Binomial distributions
Home-page: UNKNOWN
Author: Tim Yang
Author-email: timonyang@gmail.com
License: UNKNOWN
Platform: UNKNOWN
